{"CR":{"hlasy":5348976,"ucast":64.47,"strana":[{"id":1,"nazev":"Strana zdravého rozumu","zkratka":"SZR","hlasy":24828,"proc":0.46},{"id":2,"nazev":"České hnutí za národní jednotu","zkratka":"ČHNJ","hlasy":216,"proc":0},{"id":3,"nazev":"Balbínova poetická strana","zkratka":"BPS","hlasy":6897,"proc":0.12},{"id":4,"nazev":"Liberální reformní strana","zkratka":"LiRA","hlasy":253,"proc":0},{"id":5,"nazev":"Právo a Spravedlnost - ANO tradiční rodině, NE korupci a kriminalitě","zkratka":"PaS","hlasy":12756,"proc":0.23},{"id":6,"nazev":"NEZÁVISLÍ","zkratka":"NEZ","hlasy":33030,"proc":0.61},{"id":7,"nazev":"Česká pravice","zkratka":"ČP","hlasy":395,"proc":0},{"id":8,"nazev":"Koruna Česká (monarchistická strana Čech, Moravy a Slezska)","zkratka":"KČ","hlasy":7293,"proc":0.13},{"id":9,"nazev":"Občanská demokratická strana","zkratka":"ODS","hlasy":1892475,"proc":35.38},{"id":10,"nazev":"Česká strana sociálně demokratická","zkratka":"ČSSD","hlasy":1728827,"proc":32.32},{"id":11,"nazev":"SNK Evropští demokraté","zkratka":"SNK ED","hlasy":111724,"proc":2.08},{"id":12,"nazev":"Unie svobody - Demokratická unie","zkratka":"US-DEU","hlasy":16457,"proc":0.3},{"id":13,"nazev":"Helax-Ostrava se baví","zkratka":"HOB","hlasy":1375,"proc":0.02},{"id":14,"nazev":"Pravý Blok-strana za ODVOLAT.politiků, NÍZKÉ daně, MIN.byrokracie, SPRAV.justici, REFER.a PŘÍMOU demokr. WWW.CIBULKA.NET","zkratka":"PB","hlasy":20382,"proc":0.38},{"id":15,"nazev":"4 VIZE-1.Daňový systém na A4.2.Inovace+Kvalita=Kratší prac.týden.3.Rodin.dům snadno.4.Reklama pro informaci-www.4vize.cz","zkratka":"4 VIZE","hlasy":3109,"proc":0.05},{"id":16,"nazev":"Česká strana národně socialistická","zkratka":"ČSNS2005","hlasy":1387,"proc":0.02},{"id":17,"nazev":"Moravané","zkratka":"M","hlasy":12552,"proc":0.23},{"id":18,"nazev":"Strana zelených","zkratka":"SZ","hlasy":336487,"proc":6.29},{"id":19,"nazev":"Humanistická strana","zkratka":"H.S.","hlasy":857,"proc":0.01},{"id":20,"nazev":"Komunistická strana Čech a Moravy","zkratka":"KSČM","hlasy":685328,"proc":12.81},{"id":21,"nazev":"Koalice pro Českou republiku","zkratka":"Koal_ČR","hlasy":8140,"proc":0.15},{"id":22,"nazev":"Národní strana","zkratka":"NS","hlasy":9341,"proc":0.17},{"id":23,"nazev":"Folklor i Společnost","zkratka":"FiS","hlasy":574,"proc":0.01},{"id":24,"nazev":"Křesťanská a demokratická unie - Československá strana lidová","zkratka":"KDU-ČSL","hlasy":386706,"proc":7.22},{"id":25,"nazev":"NEZÁVISLÍ DEMOKRATÉ (předseda V.Železný)","zkratka":"NEZ/DEM","hlasy":36708,"proc":0.68},{"id":26,"nazev":"STRANA ROVNOST ŠANCÍ","zkratka":"SRŠ","hlasy":10879,"proc":0.2}]},"kraje":[{"id":1,"nazev":"Hl. m. Praha","mandaty":25,"hlasy":656495,"strany":[{"id":1,"nazev":"Strana zdravého rozumu","zkratka":"SZR","hlasy":2039,"mandaty":0},{"id":3,"nazev":"Balbínova poetická strana","zkratka":"BPS","hlasy":1073,"mandaty":0},{"id":5,"nazev":"Právo a Spravedlnost - ANO tradiční rodině, NE korupci a kriminalitě","zkratka":"PaS","hlasy":937,"mandaty":0},{"id":6,"nazev":"NEZÁVISLÍ","zkratka":"NEZ","hlasy":1763,"mandaty":0},{"id":7,"nazev":"Česká pravice","zkratka":"ČP","hlasy":23,"mandaty":0},{"id":8,"nazev":"Koruna Česká (monarchistická strana Čech, Moravy a Slezska)","zkratka":"KČ","hlasy":1083,"mandaty":0},{"id":9,"nazev":"Občanská demokratická strana","zkratka":"ODS","hlasy":317224,"mandaty":14},{"id":10,"nazev":"Česká strana sociálně demokratická","zkratka":"ČSSD","hlasy":152962,"mandaty":6},{"id":11,"nazev":"SNK Evropští demokraté","zkratka":"SNK ED","hlasy":23386,"mandaty":0},{"id":12,"nazev":"Unie svobody - Demokratická unie","zkratka":"US-DEU","hlasy":1638,"mandaty":0},{"id":14,"nazev":"Pravý Blok-strana za ODVOLAT.politiků, NÍZKÉ daně, MIN.byrokracie, SPRAV.justici, REFER.a PŘÍMOU demokr. WWW.CIBULKA.NET","zkratka":"PB","hlasy":2052,"mandaty":0},{"id":15,"nazev":"4 VIZE-1.Daňový systém na A4.2.Inovace+Kvalita=Kratší prac.týden.3.Rodin.dům snadno.4.Reklama pro informaci-www.4vize.cz","zkratka":"4 VIZE","hlasy":313,"mandaty":0},{"id":16,"nazev":"Česká strana národně socialistická","zkratka":"ČSNS2005","hlasy":552,"mandaty":0},{"id":18,"nazev":"Strana zelených","zkratka":"SZ","hlasy":60384,"mandaty":2},{"id":19,"nazev":"Humanistická strana","zkratka":"H.S.","hlasy":857,"mandaty":0},{"id":20,"nazev":"Komunistická strana Čech a Moravy","zkratka":"KSČM","hlasy":51925,"mandaty":2},{"id":21,"nazev":"Koalice pro Českou republiku","zkratka":"Koal_ČR","hlasy":554,"mandaty":0},{"id":22,"nazev":"Národní strana","zkratka":"NS","hlasy":973,"mandaty":0},{"id":24,"nazev":"Křesťanská a demokratická unie - Československá strana lidová","zkratka":"KDU-ČSL","hlasy":31820,"mandaty":1},{"id":25,"nazev":"NEZÁVISLÍ DEMOKRATÉ (předseda V.Železný)","zkratka":"NEZ/DEM","hlasy":2665,"mandaty":0},{"id":26,"nazev":"STRANA ROVNOST ŠANCÍ","zkratka":"SRŠ","hlasy":2272,"mandaty":0}]},{"id":2,"nazev":"Středočeský","mandaty":23,"hlasy":620047,"strany":[{"id":1,"nazev":"Strana zdravého rozumu","zkratka":"SZR","hlasy":2998,"mandaty":0},{"id":3,"nazev":"Balbínova poetická strana","zkratka":"BPS","hlasy":1559,"mandaty":0},{"id":5,"nazev":"Právo a Spravedlnost - ANO tradiční rodině, NE korupci a kriminalitě","zkratka":"PaS","hlasy":1992,"mandaty":0},{"id":6,"nazev":"NEZÁVISLÍ","zkratka":"NEZ","hlasy":3990,"mandaty":0},{"id":7,"nazev":"Česká pravice","zkratka":"ČP","hlasy":82,"mandaty":0},{"id":8,"nazev":"Koruna Česká (monarchistická strana Čech, Moravy a Slezska)","zkratka":"KČ","hlasy":989,"mandaty":0},{"id":9,"nazev":"Občanská demokratická strana","zkratka":"ODS","hlasy":243012,"mandaty":10},{"id":10,"nazev":"Česká strana sociálně demokratická","zkratka":"ČSSD","hlasy":190607,"mandaty":8},{"id":11,"nazev":"SNK Evropští demokraté","zkratka":"SNK ED","hlasy":13055,"mandaty":0},{"id":12,"nazev":"Unie svobody - Demokratická unie","zkratka":"US-DEU","hlasy":1854,"mandaty":0},{"id":14,"nazev":"Pravý Blok-strana za ODVOLAT.politiků, NÍZKÉ daně, MIN.byrokracie, SPRAV.justici, REFER.a PŘÍMOU demokr. WWW.CIBULKA.NET","zkratka":"PB","hlasy":2420,"mandaty":0},{"id":15,"nazev":"4 VIZE-1.Daňový systém na A4.2.Inovace+Kvalita=Kratší prac.týden.3.Rodin.dům snadno.4.Reklama pro informaci-www.4vize.cz","zkratka":"4 VIZE","hlasy":474,"mandaty":0},{"id":18,"nazev":"Strana zelených","zkratka":"SZ","hlasy":37219,"mandaty":1},{"id":20,"nazev":"Komunistická strana Čech a Moravy","zkratka":"KSČM","hlasy":79964,"mandaty":3},{"id":21,"nazev":"Koalice pro Českou republiku","zkratka":"Koal_ČR","hlasy":1132,"mandaty":0},{"id":22,"nazev":"Národní strana","zkratka":"NS","hlasy":1257,"mandaty":0},{"id":24,"nazev":"Křesťanská a demokratická unie - Československá strana lidová","zkratka":"KDU-ČSL","hlasy":30207,"mandaty":1},{"id":25,"nazev":"NEZÁVISLÍ DEMOKRATÉ (předseda V.Železný)","zkratka":"NEZ/DEM","hlasy":5723,"mandaty":0},{"id":26,"nazev":"STRANA ROVNOST ŠANCÍ","zkratka":"SRŠ","hlasy":1513,"mandaty":0}]},{"id":3,"nazev":"Jihočeský","mandaty":13,"hlasy":337387,"strany":[{"id":1,"nazev":"Strana zdravého rozumu","zkratka":"SZR","hlasy":1444,"mandaty":0},{"id":3,"nazev":"Balbínova poetická strana","zkratka":"BPS","hlasy":417,"mandaty":0},{"id":5,"nazev":"Právo a Spravedlnost - ANO tradiční rodině, NE korupci a kriminalitě","zkratka":"PaS","hlasy":694,"mandaty":0},{"id":6,"nazev":"NEZÁVISLÍ","zkratka":"NEZ","hlasy":2402,"mandaty":0},{"id":8,"nazev":"Koruna Česká (monarchistická strana Čech, Moravy a Slezska)","zkratka":"KČ","hlasy":559,"mandaty":0},{"id":9,"nazev":"Občanská demokratická strana","zkratka":"ODS","hlasy":123804,"mandaty":6},{"id":10,"nazev":"Česká strana sociálně demokratická","zkratka":"ČSSD","hlasy":102833,"mandaty":4},{"id":11,"nazev":"SNK Evropští demokraté","zkratka":"SNK ED","hlasy":6570,"mandaty":0},{"id":12,"nazev":"Unie svobody - Demokratická unie","zkratka":"US-DEU","hlasy":1008,"mandaty":0},{"id":14,"nazev":"Pravý Blok-strana za ODVOLAT.politiků, NÍZKÉ daně, MIN.byrokracie, SPRAV.justici, REFER.a PŘÍMOU demokr. WWW.CIBULKA.NET","zkratka":"PB","hlasy":1393,"mandaty":0},{"id":15,"nazev":"4 VIZE-1.Daňový systém na A4.2.Inovace+Kvalita=Kratší prac.týden.3.Rodin.dům snadno.4.Reklama pro informaci-www.4vize.cz","zkratka":"4 VIZE","hlasy":234,"mandaty":0},{"id":17,"nazev":"Moravané","zkratka":"M","hlasy":377,"mandaty":0},{"id":18,"nazev":"Strana zelených","zkratka":"SZ","hlasy":19924,"mandaty":0},{"id":20,"nazev":"Komunistická strana Čech a Moravy","zkratka":"KSČM","hlasy":45099,"mandaty":2},{"id":21,"nazev":"Koalice pro Českou republiku","zkratka":"Koal_ČR","hlasy":421,"mandaty":0},{"id":22,"nazev":"Národní strana","zkratka":"NS","hlasy":524,"mandaty":0},{"id":24,"nazev":"Křesťanská a demokratická unie - Československá strana lidová","zkratka":"KDU-ČSL","hlasy":27630,"mandaty":1},{"id":25,"nazev":"NEZÁVISLÍ DEMOKRATÉ (předseda V.Železný)","zkratka":"NEZ/DEM","hlasy":1486,"mandaty":0},{"id":26,"nazev":"STRANA ROVNOST ŠANCÍ","zkratka":"SRŠ","hlasy":568,"mandaty":0}]},{"id":4,"nazev":"Plzeňský","mandaty":11,"hlasy":289049,"strany":[{"id":1,"nazev":"Strana zdravého rozumu","zkratka":"SZR","hlasy":1783,"mandaty":0},{"id":3,"nazev":"Balbínova poetická strana","zkratka":"BPS","hlasy":356,"mandaty":0},{"id":5,"nazev":"Právo a Spravedlnost - ANO tradiční rodině, NE korupci a kriminalitě","zkratka":"PaS","hlasy":1084,"mandaty":0},{"id":6,"nazev":"NEZÁVISLÍ","zkratka":"NEZ","hlasy":2184,"mandaty":0},{"id":8,"nazev":"Koruna Česká (monarchistická strana Čech, Moravy a Slezska)","zkratka":"KČ","hlasy":604,"mandaty":0},{"id":9,"nazev":"Občanská demokratická strana","zkratka":"ODS","hlasy":105391,"mandaty":5},{"id":10,"nazev":"Česká strana sociálně demokratická","zkratka":"ČSSD","hlasy":91606,"mandaty":4},{"id":11,"nazev":"SNK Evropští demokraté","zkratka":"SNK ED","hlasy":5912,"mandaty":0},{"id":12,"nazev":"Unie svobody - Demokratická unie","zkratka":"US-DEU","hlasy":973,"mandaty":0},{"id":14,"nazev":"Pravý Blok-strana za ODVOLAT.politiků, NÍZKÉ daně, MIN.byrokracie, SPRAV.justici, REFER.a PŘÍMOU demokr. WWW.CIBULKA.NET","zkratka":"PB","hlasy":1339,"mandaty":0},{"id":15,"nazev":"4 VIZE-1.Daňový systém na A4.2.Inovace+Kvalita=Kratší prac.týden.3.Rodin.dům snadno.4.Reklama pro informaci-www.4vize.cz","zkratka":"4 VIZE","hlasy":233,"mandaty":0},{"id":18,"nazev":"Strana zelených","zkratka":"SZ","hlasy":17090,"mandaty":0},{"id":20,"nazev":"Komunistická strana Čech a Moravy","zkratka":"KSČM","hlasy":40578,"mandaty":2},{"id":21,"nazev":"Koalice pro Českou republiku","zkratka":"Koal_ČR","hlasy":560,"mandaty":0},{"id":22,"nazev":"Národní strana","zkratka":"NS","hlasy":495,"mandaty":0},{"id":24,"nazev":"Křesťanská a demokratická unie - Československá strana lidová","zkratka":"KDU-ČSL","hlasy":16338,"mandaty":0},{"id":25,"nazev":"NEZÁVISLÍ DEMOKRATÉ (předseda V.Železný)","zkratka":"NEZ/DEM","hlasy":1912,"mandaty":0},{"id":26,"nazev":"STRANA ROVNOST ŠANCÍ","zkratka":"SRŠ","hlasy":611,"mandaty":0}]},{"id":5,"nazev":"Karlovarský","mandaty":5,"hlasy":137117,"strany":[{"id":1,"nazev":"Strana zdravého rozumu","zkratka":"SZR","hlasy":967,"mandaty":0},{"id":3,"nazev":"Balbínova poetická strana","zkratka":"BPS","hlasy":207,"mandaty":0},{"id":5,"nazev":"Právo a Spravedlnost - ANO tradiční rodině, NE korupci a kriminalitě","zkratka":"PaS","hlasy":404,"mandaty":0},{"id":6,"nazev":"NEZÁVISLÍ","zkratka":"NEZ","hlasy":441,"mandaty":0},{"id":8,"nazev":"Koruna Česká (monarchistická strana Čech, Moravy a Slezska)","zkratka":"KČ","hlasy":206,"mandaty":0},{"id":9,"nazev":"Občanská demokratická strana","zkratka":"ODS","hlasy":49189,"mandaty":2},{"id":10,"nazev":"Česká strana sociálně demokratická","zkratka":"ČSSD","hlasy":44887,"mandaty":2},{"id":11,"nazev":"SNK Evropští demokraté","zkratka":"SNK ED","hlasy":2312,"mandaty":0},{"id":12,"nazev":"Unie svobody - Demokratická unie","zkratka":"US-DEU","hlasy":725,"mandaty":0},{"id":14,"nazev":"Pravý Blok-strana za ODVOLAT.politiků, NÍZKÉ daně, MIN.byrokracie, SPRAV.justici, REFER.a PŘÍMOU demokr. WWW.CIBULKA.NET","zkratka":"PB","hlasy":846,"mandaty":0},{"id":15,"nazev":"4 VIZE-1.Daňový systém na A4.2.Inovace+Kvalita=Kratší prac.týden.3.Rodin.dům snadno.4.Reklama pro informaci-www.4vize.cz","zkratka":"4 VIZE","hlasy":121,"mandaty":0},{"id":18,"nazev":"Strana zelených","zkratka":"SZ","hlasy":9206,"mandaty":0},{"id":20,"nazev":"Komunistická strana Čech a Moravy","zkratka":"KSČM","hlasy":20323,"mandaty":1},{"id":21,"nazev":"Koalice pro Českou republiku","zkratka":"Koal_ČR","hlasy":259,"mandaty":0},{"id":22,"nazev":"Národní strana","zkratka":"NS","hlasy":532,"mandaty":0},{"id":24,"nazev":"Křesťanská a demokratická unie - Československá strana lidová","zkratka":"KDU-ČSL","hlasy":4723,"mandaty":0},{"id":25,"nazev":"NEZÁVISLÍ DEMOKRATÉ (předseda V.Železný)","zkratka":"NEZ/DEM","hlasy":1296,"mandaty":0},{"id":26,"nazev":"STRANA ROVNOST ŠANCÍ","zkratka":"SRŠ","hlasy":473,"mandaty":0}]},{"id":6,"nazev":"Ústecký","mandaty":14,"hlasy":374736,"strany":[{"id":1,"nazev":"Strana zdravého rozumu","zkratka":"SZR","hlasy":1771,"mandaty":0},{"id":2,"nazev":"České hnutí za národní jednotu","zkratka":"ČHNJ","hlasy":216,"mandaty":0},{"id":3,"nazev":"Balbínova poetická strana","zkratka":"BPS","hlasy":452,"mandaty":0},{"id":5,"nazev":"Právo a Spravedlnost - ANO tradiční rodině, NE korupci a kriminalitě","zkratka":"PaS","hlasy":1387,"mandaty":0},{"id":6,"nazev":"NEZÁVISLÍ","zkratka":"NEZ","hlasy":2887,"mandaty":0},{"id":7,"nazev":"Česká pravice","zkratka":"ČP","hlasy":124,"mandaty":0},{"id":8,"nazev":"Koruna Česká (monarchistická strana Čech, Moravy a Slezska)","zkratka":"KČ","hlasy":418,"mandaty":0},{"id":9,"nazev":"Občanská demokratická strana","zkratka":"ODS","hlasy":130365,"mandaty":5},{"id":10,"nazev":"Česká strana sociálně demokratická","zkratka":"ČSSD","hlasy":132895,"mandaty":6},{"id":11,"nazev":"SNK Evropští demokraté","zkratka":"SNK ED","hlasy":5372,"mandaty":0},{"id":12,"nazev":"Unie svobody - Demokratická unie","zkratka":"US-DEU","hlasy":1234,"mandaty":0},{"id":14,"nazev":"Pravý Blok-strana za ODVOLAT.politiků, NÍZKÉ daně, MIN.byrokracie, SPRAV.justici, REFER.a PŘÍMOU demokr. WWW.CIBULKA.NET","zkratka":"PB","hlasy":1367,"mandaty":0},{"id":15,"nazev":"4 VIZE-1.Daňový systém na A4.2.Inovace+Kvalita=Kratší prac.týden.3.Rodin.dům snadno.4.Reklama pro informaci-www.4vize.cz","zkratka":"4 VIZE","hlasy":218,"mandaty":0},{"id":18,"nazev":"Strana zelených","zkratka":"SZ","hlasy":22616,"mandaty":1},{"id":20,"nazev":"Komunistická strana Čech a Moravy","zkratka":"KSČM","hlasy":60175,"mandaty":2},{"id":21,"nazev":"Koalice pro Českou republiku","zkratka":"Koal_ČR","hlasy":580,"mandaty":0},{"id":22,"nazev":"Národní strana","zkratka":"NS","hlasy":861,"mandaty":0},{"id":24,"nazev":"Křesťanská a demokratická unie - Československá strana lidová","zkratka":"KDU-ČSL","hlasy":8365,"mandaty":0},{"id":25,"nazev":"NEZÁVISLÍ DEMOKRATÉ (předseda V.Železný)","zkratka":"NEZ/DEM","hlasy":2821,"mandaty":0},{"id":26,"nazev":"STRANA ROVNOST ŠANCÍ","zkratka":"SRŠ","hlasy":612,"mandaty":0}]},{"id":7,"nazev":"Liberecký","mandaty":8,"hlasy":215510,"strany":[{"id":1,"nazev":"Strana zdravého rozumu","zkratka":"SZR","hlasy":1437,"mandaty":0},{"id":3,"nazev":"Balbínova poetická strana","zkratka":"BPS","hlasy":305,"mandaty":0},{"id":5,"nazev":"Právo a Spravedlnost - ANO tradiční rodině, NE korupci a kriminalitě","zkratka":"PaS","hlasy":460,"mandaty":0},{"id":6,"nazev":"NEZÁVISLÍ","zkratka":"NEZ","hlasy":2053,"mandaty":0},{"id":8,"nazev":"Koruna Česká (monarchistická strana Čech, Moravy a Slezska)","zkratka":"KČ","hlasy":294,"mandaty":0},{"id":9,"nazev":"Občanská demokratická strana","zkratka":"ODS","hlasy":83647,"mandaty":4},{"id":10,"nazev":"Česká strana sociálně demokratická","zkratka":"ČSSD","hlasy":63181,"mandaty":3},{"id":11,"nazev":"SNK Evropští demokraté","zkratka":"SNK ED","hlasy":4304,"mandaty":0},{"id":12,"nazev":"Unie svobody - Demokratická unie","zkratka":"US-DEU","hlasy":753,"mandaty":0},{"id":14,"nazev":"Pravý Blok-strana za ODVOLAT.politiků, NÍZKÉ daně, MIN.byrokracie, SPRAV.justici, REFER.a PŘÍMOU demokr. WWW.CIBULKA.NET","zkratka":"PB","hlasy":1139,"mandaty":0},{"id":15,"nazev":"4 VIZE-1.Daňový systém na A4.2.Inovace+Kvalita=Kratší prac.týden.3.Rodin.dům snadno.4.Reklama pro informaci-www.4vize.cz","zkratka":"4 VIZE","hlasy":257,"mandaty":0},{"id":18,"nazev":"Strana zelených","zkratka":"SZ","hlasy":20646,"mandaty":0},{"id":20,"nazev":"Komunistická strana Čech a Moravy","zkratka":"KSČM","hlasy":24823,"mandaty":1},{"id":21,"nazev":"Koalice pro Českou republiku","zkratka":"Koal_ČR","hlasy":474,"mandaty":0},{"id":22,"nazev":"Národní strana","zkratka":"NS","hlasy":568,"mandaty":0},{"id":24,"nazev":"Křesťanská a demokratická unie - Československá strana lidová","zkratka":"KDU-ČSL","hlasy":9131,"mandaty":0},{"id":25,"nazev":"NEZÁVISLÍ DEMOKRATÉ (předseda V.Železný)","zkratka":"NEZ/DEM","hlasy":1538,"mandaty":0},{"id":26,"nazev":"STRANA ROVNOST ŠANCÍ","zkratka":"SRŠ","hlasy":500,"mandaty":0}]},{"id":8,"nazev":"Královéhradecký","mandaty":11,"hlasy":295931,"strany":[{"id":1,"nazev":"Strana zdravého rozumu","zkratka":"SZR","hlasy":1770,"mandaty":0},{"id":3,"nazev":"Balbínova poetická strana","zkratka":"BPS","hlasy":380,"mandaty":0},{"id":5,"nazev":"Právo a Spravedlnost - ANO tradiční rodině, NE korupci a kriminalitě","zkratka":"PaS","hlasy":688,"mandaty":0},{"id":6,"nazev":"NEZÁVISLÍ","zkratka":"NEZ","hlasy":1652,"mandaty":0},{"id":8,"nazev":"Koruna Česká (monarchistická strana Čech, Moravy a Slezska)","zkratka":"KČ","hlasy":593,"mandaty":0},{"id":9,"nazev":"Občanská demokratická strana","zkratka":"ODS","hlasy":111466,"mandaty":5},{"id":10,"nazev":"Česká strana sociálně demokratická","zkratka":"ČSSD","hlasy":89204,"mandaty":4},{"id":11,"nazev":"SNK Evropští demokraté","zkratka":"SNK ED","hlasy":9126,"mandaty":0},{"id":12,"nazev":"Unie svobody - Demokratická unie","zkratka":"US-DEU","hlasy":1431,"mandaty":0},{"id":14,"nazev":"Pravý Blok-strana za ODVOLAT.politiků, NÍZKÉ daně, MIN.byrokracie, SPRAV.justici, REFER.a PŘÍMOU demokr. WWW.CIBULKA.NET","zkratka":"PB","hlasy":1712,"mandaty":0},{"id":15,"nazev":"4 VIZE-1.Daňový systém na A4.2.Inovace+Kvalita=Kratší prac.týden.3.Rodin.dům snadno.4.Reklama pro informaci-www.4vize.cz","zkratka":"4 VIZE","hlasy":224,"mandaty":0},{"id":18,"nazev":"Strana zelených","zkratka":"SZ","hlasy":19819,"mandaty":0},{"id":20,"nazev":"Komunistická strana Čech a Moravy","zkratka":"KSČM","hlasy":34093,"mandaty":1},{"id":21,"nazev":"Koalice pro Českou republiku","zkratka":"Koal_ČR","hlasy":603,"mandaty":0},{"id":22,"nazev":"Národní strana","zkratka":"NS","hlasy":641,"mandaty":0},{"id":24,"nazev":"Křesťanská a demokratická unie - Československá strana lidová","zkratka":"KDU-ČSL","hlasy":19893,"mandaty":1},{"id":25,"nazev":"NEZÁVISLÍ DEMOKRATÉ (předseda V.Železný)","zkratka":"NEZ/DEM","hlasy":2056,"mandaty":0},{"id":26,"nazev":"STRANA ROVNOST ŠANCÍ","zkratka":"SRŠ","hlasy":580,"mandaty":0}]},{"id":9,"nazev":"Pardubický","mandaty":10,"hlasy":273921,"strany":[{"id":1,"nazev":"Strana zdravého rozumu","zkratka":"SZR","hlasy":1447,"mandaty":0},{"id":3,"nazev":"Balbínova poetická strana","zkratka":"BPS","hlasy":323,"mandaty":0},{"id":5,"nazev":"Právo a Spravedlnost - ANO tradiční rodině, NE korupci a kriminalitě","zkratka":"PaS","hlasy":637,"mandaty":0},{"id":6,"nazev":"NEZÁVISLÍ","zkratka":"NEZ","hlasy":2381,"mandaty":0},{"id":8,"nazev":"Koruna Česká (monarchistická strana Čech, Moravy a Slezska)","zkratka":"KČ","hlasy":260,"mandaty":0},{"id":9,"nazev":"Občanská demokratická strana","zkratka":"ODS","hlasy":91113,"mandaty":4},{"id":10,"nazev":"Česká strana sociálně demokratická","zkratka":"ČSSD","hlasy":90268,"mandaty":4},{"id":11,"nazev":"SNK Evropští demokraté","zkratka":"SNK ED","hlasy":6641,"mandaty":0},{"id":12,"nazev":"Unie svobody - Demokratická unie","zkratka":"US-DEU","hlasy":936,"mandaty":0},{"id":14,"nazev":"Pravý Blok-strana za ODVOLAT.politiků, NÍZKÉ daně, MIN.byrokracie, SPRAV.justici, REFER.a PŘÍMOU demokr. WWW.CIBULKA.NET","zkratka":"PB","hlasy":1104,"mandaty":0},{"id":15,"nazev":"4 VIZE-1.Daňový systém na A4.2.Inovace+Kvalita=Kratší prac.týden.3.Rodin.dům snadno.4.Reklama pro informaci-www.4vize.cz","zkratka":"4 VIZE","hlasy":191,"mandaty":0},{"id":17,"nazev":"Moravané","zkratka":"M","hlasy":445,"mandaty":0},{"id":18,"nazev":"Strana zelených","zkratka":"SZ","hlasy":17148,"mandaty":0},{"id":20,"nazev":"Komunistická strana Čech a Moravy","zkratka":"KSČM","hlasy":33956,"mandaty":1},{"id":21,"nazev":"Koalice pro Českou republiku","zkratka":"Koal_ČR","hlasy":718,"mandaty":0},{"id":22,"nazev":"Národní strana","zkratka":"NS","hlasy":368,"mandaty":0},{"id":24,"nazev":"Křesťanská a demokratická unie - Československá strana lidová","zkratka":"KDU-ČSL","hlasy":24023,"mandaty":1},{"id":25,"nazev":"NEZÁVISLÍ DEMOKRATÉ (předseda V.Železný)","zkratka":"NEZ/DEM","hlasy":1582,"mandaty":0},{"id":26,"nazev":"STRANA ROVNOST ŠANCÍ","zkratka":"SRŠ","hlasy":380,"mandaty":0}]},{"id":10,"nazev":"Vysočina","mandaty":10,"hlasy":275997,"strany":[{"id":1,"nazev":"Strana zdravého rozumu","zkratka":"SZR","hlasy":1028,"mandaty":0},{"id":3,"nazev":"Balbínova poetická strana","zkratka":"BPS","hlasy":293,"mandaty":0},{"id":5,"nazev":"Právo a Spravedlnost - ANO tradiční rodině, NE korupci a kriminalitě","zkratka":"PaS","hlasy":724,"mandaty":0},{"id":6,"nazev":"NEZÁVISLÍ","zkratka":"NEZ","hlasy":976,"mandaty":0},{"id":8,"nazev":"Koruna Česká (monarchistická strana Čech, Moravy a Slezska)","zkratka":"KČ","hlasy":314,"mandaty":0},{"id":9,"nazev":"Občanská demokratická strana","zkratka":"ODS","hlasy":76393,"mandaty":3},{"id":10,"nazev":"Česká strana sociálně demokratická","zkratka":"ČSSD","hlasy":97568,"mandaty":4},{"id":11,"nazev":"SNK Evropští demokraté","zkratka":"SNK ED","hlasy":5525,"mandaty":0},{"id":12,"nazev":"Unie svobody - Demokratická unie","zkratka":"US-DEU","hlasy":931,"mandaty":0},{"id":14,"nazev":"Pravý Blok-strana za ODVOLAT.politiků, NÍZKÉ daně, MIN.byrokracie, SPRAV.justici, REFER.a PŘÍMOU demokr. WWW.CIBULKA.NET","zkratka":"PB","hlasy":1110,"mandaty":0},{"id":15,"nazev":"4 VIZE-1.Daňový systém na A4.2.Inovace+Kvalita=Kratší prac.týden.3.Rodin.dům snadno.4.Reklama pro informaci-www.4vize.cz","zkratka":"4 VIZE","hlasy":155,"mandaty":0},{"id":17,"nazev":"Moravané","zkratka":"M","hlasy":622,"mandaty":0},{"id":18,"nazev":"Strana zelených","zkratka":"SZ","hlasy":13514,"mandaty":0},{"id":20,"nazev":"Komunistická strana Čech a Moravy","zkratka":"KSČM","hlasy":40480,"mandaty":2},{"id":21,"nazev":"Koalice pro Českou republiku","zkratka":"Koal_ČR","hlasy":614,"mandaty":0},{"id":22,"nazev":"Národní strana","zkratka":"NS","hlasy":344,"mandaty":0},{"id":24,"nazev":"Křesťanská a demokratická unie - Československá strana lidová","zkratka":"KDU-ČSL","hlasy":33587,"mandaty":1},{"id":25,"nazev":"NEZÁVISLÍ DEMOKRATÉ (předseda V.Železný)","zkratka":"NEZ/DEM","hlasy":1403,"mandaty":0},{"id":26,"nazev":"STRANA ROVNOST ŠANCÍ","zkratka":"SRŠ","hlasy":416,"mandaty":0}]},{"id":11,"nazev":"Jihomoravský","mandaty":23,"hlasy":608804,"strany":[{"id":1,"nazev":"Strana zdravého rozumu","zkratka":"SZR","hlasy":1698,"mandaty":0},{"id":3,"nazev":"Balbínova poetická strana","zkratka":"BPS","hlasy":589,"mandaty":0},{"id":4,"nazev":"Liberální reformní strana","zkratka":"LiRA","hlasy":253,"mandaty":0},{"id":5,"nazev":"Právo a Spravedlnost - ANO tradiční rodině, NE korupci a kriminalitě","zkratka":"PaS","hlasy":1015,"mandaty":0},{"id":6,"nazev":"NEZÁVISLÍ","zkratka":"NEZ","hlasy":2850,"mandaty":0},{"id":7,"nazev":"Česká pravice","zkratka":"ČP","hlasy":45,"mandaty":0},{"id":8,"nazev":"Koruna Česká (monarchistická strana Čech, Moravy a Slezska)","zkratka":"KČ","hlasy":821,"mandaty":0},{"id":9,"nazev":"Občanská demokratická strana","zkratka":"ODS","hlasy":186779,"mandaty":8},{"id":10,"nazev":"Česká strana sociálně demokratická","zkratka":"ČSSD","hlasy":200619,"mandaty":8},{"id":11,"nazev":"SNK Evropští demokraté","zkratka":"SNK ED","hlasy":7343,"mandaty":0},{"id":12,"nazev":"Unie svobody - Demokratická unie","zkratka":"US-DEU","hlasy":1495,"mandaty":0},{"id":14,"nazev":"Pravý Blok-strana za ODVOLAT.politiků, NÍZKÉ daně, MIN.byrokracie, SPRAV.justici, REFER.a PŘÍMOU demokr. WWW.CIBULKA.NET","zkratka":"PB","hlasy":2426,"mandaty":0},{"id":15,"nazev":"4 VIZE-1.Daňový systém na A4.2.Inovace+Kvalita=Kratší prac.týden.3.Rodin.dům snadno.4.Reklama pro informaci-www.4vize.cz","zkratka":"4 VIZE","hlasy":201,"mandaty":0},{"id":16,"nazev":"Česká strana národně socialistická","zkratka":"ČSNS2005","hlasy":835,"mandaty":0},{"id":17,"nazev":"Moravané","zkratka":"M","hlasy":4677,"mandaty":0},{"id":18,"nazev":"Strana zelených","zkratka":"SZ","hlasy":37771,"mandaty":1},{"id":20,"nazev":"Komunistická strana Čech a Moravy","zkratka":"KSČM","hlasy":83687,"mandaty":3},{"id":21,"nazev":"Koalice pro Českou republiku","zkratka":"Koal_ČR","hlasy":522,"mandaty":0},{"id":22,"nazev":"Národní strana","zkratka":"NS","hlasy":542,"mandaty":0},{"id":23,"nazev":"Folklor i Společnost","zkratka":"FiS","hlasy":574,"mandaty":0},{"id":24,"nazev":"Křesťanská a demokratická unie - Československá strana lidová","zkratka":"KDU-ČSL","hlasy":67865,"mandaty":3},{"id":25,"nazev":"NEZÁVISLÍ DEMOKRATÉ (předseda V.Železný)","zkratka":"NEZ/DEM","hlasy":5171,"mandaty":0},{"id":26,"nazev":"STRANA ROVNOST ŠANCÍ","zkratka":"SRŠ","hlasy":1026,"mandaty":0}]},{"id":12,"nazev":"Olomoucký","mandaty":12,"hlasy":333849,"strany":[{"id":1,"nazev":"Strana zdravého rozumu","zkratka":"SZR","hlasy":1627,"mandaty":0},{"id":3,"nazev":"Balbínova poetická strana","zkratka":"BPS","hlasy":183,"mandaty":0},{"id":5,"nazev":"Právo a Spravedlnost - ANO tradiční rodině, NE korupci a kriminalitě","zkratka":"PaS","hlasy":1073,"mandaty":0},{"id":6,"nazev":"NEZÁVISLÍ","zkratka":"NEZ","hlasy":3295,"mandaty":0},{"id":7,"nazev":"Česká pravice","zkratka":"ČP","hlasy":41,"mandaty":0},{"id":8,"nazev":"Koruna Česká (monarchistická strana Čech, Moravy a Slezska)","zkratka":"KČ","hlasy":337,"mandaty":0},{"id":9,"nazev":"Občanská demokratická strana","zkratka":"ODS","hlasy":101151,"mandaty":4},{"id":10,"nazev":"Česká strana sociálně demokratická","zkratka":"ČSSD","hlasy":118334,"mandaty":5},{"id":11,"nazev":"SNK Evropští demokraté","zkratka":"SNK ED","hlasy":3821,"mandaty":0},{"id":12,"nazev":"Unie svobody - Demokratická unie","zkratka":"US-DEU","hlasy":764,"mandaty":0},{"id":14,"nazev":"Pravý Blok-strana za ODVOLAT.politiků, NÍZKÉ daně, MIN.byrokracie, SPRAV.justici, REFER.a PŘÍMOU demokr. WWW.CIBULKA.NET","zkratka":"PB","hlasy":1094,"mandaty":0},{"id":15,"nazev":"4 VIZE-1.Daňový systém na A4.2.Inovace+Kvalita=Kratší prac.týden.3.Rodin.dům snadno.4.Reklama pro informaci-www.4vize.cz","zkratka":"4 VIZE","hlasy":186,"mandaty":0},{"id":17,"nazev":"Moravané","zkratka":"M","hlasy":2650,"mandaty":0},{"id":18,"nazev":"Strana zelených","zkratka":"SZ","hlasy":18398,"mandaty":0},{"id":20,"nazev":"Komunistická strana Čech a Moravy","zkratka":"KSČM","hlasy":49026,"mandaty":2},{"id":21,"nazev":"Koalice pro Českou republiku","zkratka":"Koal_ČR","hlasy":598,"mandaty":0},{"id":22,"nazev":"Národní strana","zkratka":"NS","hlasy":478,"mandaty":0},{"id":24,"nazev":"Křesťanská a demokratická unie - Československá strana lidová","zkratka":"KDU-ČSL","hlasy":27609,"mandaty":1},{"id":25,"nazev":"NEZÁVISLÍ DEMOKRATÉ (předseda V.Železný)","zkratka":"NEZ/DEM","hlasy":2636,"mandaty":0},{"id":26,"nazev":"STRANA ROVNOST ŠANCÍ","zkratka":"SRŠ","hlasy":548,"mandaty":0}]},{"id":13,"nazev":"Zlínský","mandaty":12,"hlasy":319933,"strany":[{"id":1,"nazev":"Strana zdravého rozumu","zkratka":"SZR","hlasy":1405,"mandaty":0},{"id":3,"nazev":"Balbínova poetická strana","zkratka":"BPS","hlasy":335,"mandaty":0},{"id":5,"nazev":"Právo a Spravedlnost - ANO tradiční rodině, NE korupci a kriminalitě","zkratka":"PaS","hlasy":617,"mandaty":0},{"id":6,"nazev":"NEZÁVISLÍ","zkratka":"NEZ","hlasy":1966,"mandaty":0},{"id":7,"nazev":"Česká pravice","zkratka":"ČP","hlasy":38,"mandaty":0},{"id":8,"nazev":"Koruna Česká (monarchistická strana Čech, Moravy a Slezska)","zkratka":"KČ","hlasy":395,"mandaty":0},{"id":9,"nazev":"Občanská demokratická strana","zkratka":"ODS","hlasy":101376,"mandaty":4},{"id":10,"nazev":"Česká strana sociálně demokratická","zkratka":"ČSSD","hlasy":106481,"mandaty":5},{"id":11,"nazev":"SNK Evropští demokraté","zkratka":"SNK ED","hlasy":6390,"mandaty":0},{"id":12,"nazev":"Unie svobody - Demokratická unie","zkratka":"US-DEU","hlasy":1089,"mandaty":0},{"id":14,"nazev":"Pravý Blok-strana za ODVOLAT.politiků, NÍZKÉ daně, MIN.byrokracie, SPRAV.justici, REFER.a PŘÍMOU demokr. WWW.CIBULKA.NET","zkratka":"PB","hlasy":929,"mandaty":0},{"id":15,"nazev":"4 VIZE-1.Daňový systém na A4.2.Inovace+Kvalita=Kratší prac.týden.3.Rodin.dům snadno.4.Reklama pro informaci-www.4vize.cz","zkratka":"4 VIZE","hlasy":116,"mandaty":0},{"id":17,"nazev":"Moravané","zkratka":"M","hlasy":2289,"mandaty":0},{"id":18,"nazev":"Strana zelených","zkratka":"SZ","hlasy":16224,"mandaty":0},{"id":20,"nazev":"Komunistická strana Čech a Moravy","zkratka":"KSČM","hlasy":35998,"mandaty":1},{"id":21,"nazev":"Koalice pro Českou republiku","zkratka":"Koal_ČR","hlasy":296,"mandaty":0},{"id":22,"nazev":"Národní strana","zkratka":"NS","hlasy":282,"mandaty":0},{"id":24,"nazev":"Křesťanská a demokratická unie - Československá strana lidová","zkratka":"KDU-ČSL","hlasy":41663,"mandaty":2},{"id":25,"nazev":"NEZÁVISLÍ DEMOKRATÉ (předseda V.Železný)","zkratka":"NEZ/DEM","hlasy":1592,"mandaty":0},{"id":26,"nazev":"STRANA ROVNOST ŠANCÍ","zkratka":"SRŠ","hlasy":452,"mandaty":0}]},{"id":14,"nazev":"Moravskoslezský","mandaty":23,"hlasy":610200,"strany":[{"id":1,"nazev":"Strana zdravého rozumu","zkratka":"SZR","hlasy":3414,"mandaty":0},{"id":3,"nazev":"Balbínova poetická strana","zkratka":"BPS","hlasy":425,"mandaty":0},{"id":5,"nazev":"Právo a Spravedlnost - ANO tradiční rodině, NE korupci a kriminalitě","zkratka":"PaS","hlasy":1044,"mandaty":0},{"id":6,"nazev":"NEZÁVISLÍ","zkratka":"NEZ","hlasy":4190,"mandaty":0},{"id":7,"nazev":"Česká pravice","zkratka":"ČP","hlasy":42,"mandaty":0},{"id":8,"nazev":"Koruna Česká (monarchistická strana Čech, Moravy a Slezska)","zkratka":"KČ","hlasy":420,"mandaty":0},{"id":9,"nazev":"Občanská demokratická strana","zkratka":"ODS","hlasy":171565,"mandaty":7},{"id":10,"nazev":"Česká strana sociálně demokratická","zkratka":"ČSSD","hlasy":247382,"mandaty":11},{"id":11,"nazev":"SNK Evropští demokraté","zkratka":"SNK ED","hlasy":11967,"mandaty":0},{"id":12,"nazev":"Unie svobody - Demokratická unie","zkratka":"US-DEU","hlasy":1626,"mandaty":0},{"id":13,"nazev":"Helax-Ostrava se baví","zkratka":"HOB","hlasy":1375,"mandaty":0},{"id":14,"nazev":"Pravý Blok-strana za ODVOLAT.politiků, NÍZKÉ daně, MIN.byrokracie, SPRAV.justici, REFER.a PŘÍMOU demokr. WWW.CIBULKA.NET","zkratka":"PB","hlasy":1451,"mandaty":0},{"id":15,"nazev":"4 VIZE-1.Daňový systém na A4.2.Inovace+Kvalita=Kratší prac.týden.3.Rodin.dům snadno.4.Reklama pro informaci-www.4vize.cz","zkratka":"4 VIZE","hlasy":186,"mandaty":0},{"id":17,"nazev":"Moravané","zkratka":"M","hlasy":1492,"mandaty":0},{"id":18,"nazev":"Strana zelených","zkratka":"SZ","hlasy":26528,"mandaty":1},{"id":20,"nazev":"Komunistická strana Čech a Moravy","zkratka":"KSČM","hlasy":85201,"mandaty":3},{"id":21,"nazev":"Koalice pro Českou republiku","zkratka":"Koal_ČR","hlasy":809,"mandaty":0},{"id":22,"nazev":"Národní strana","zkratka":"NS","hlasy":1476,"mandaty":0},{"id":24,"nazev":"Křesťanská a demokratická unie - Československá strana lidová","zkratka":"KDU-ČSL","hlasy":43852,"mandaty":1},{"id":25,"nazev":"NEZÁVISLÍ DEMOKRATÉ (předseda V.Železný)","zkratka":"NEZ/DEM","hlasy":4827,"mandaty":0},{"id":26,"nazev":"STRANA ROVNOST ŠANCÍ","zkratka":"SRŠ","hlasy":928,"mandaty":0}]}]}